blackclue.py
blackvue_gps.py
blackvue_gps-2018.7.16.dist-info/METADATA
blackvue_gps-2018.7.16.dist-info/RECORD
blackvue_gps-2018.7.16.dist-info/WHEEL
blackvue_gps-2018.7.16.dist-info/entry_points.txt
blackvue_gps-2018.7.16.dist-info/top_level.txt
