Metadata-Version: 2.1
Name: blackvue-gps
Version: 2018.7.16
Summary: Parse GPS records created by BlackVue Dashcams.
Home-page: https://github.com/bartbroere/blackvue-gps/
Author: Bart Broere
Author-email: maiil@bartbroere.eu
License: MIT License
Keywords: blackvue gps dashcam nmea parse parser
Platform: UNKNOWN
Classifier: License :: OSI Approved :: MIT License
Classifier: Programming Language :: Python :: 3 :: Only
Classifier: Programming Language :: Python :: 3.4
Classifier: Programming Language :: Python :: 3.5
Classifier: Programming Language :: Python :: 3.6
Classifier: Programming Language :: Python :: 3.7
Classifier: Topic :: Utilities
Requires-Dist: click
Requires-Dist: docopt
Requires-Dist: pynmea2
Requires-Dist: pymp4
